{"9":["MT1_7-11","MT2_8-9","MT4_8-9","MT5_9","MT7_9-10","MT8_8-10","MT8_28","MT9_1","MT9_2","MT9_3-5","MT9_6-8","MT9_9","MT9_10-11","MT9_12-13","MT9_18-19","MT9_20-22","MT9_23","MT9_25-26","MT9_29-30","MT9_30-31","MT9_32-33","MT9_37-38","MT10_9-10","MT11_9","MT11_29-30","MT12_9-10","MT13_9"],"10":["MT1_7-11","MT2_10","MT4_10","MT5_10","MT7_9-10","MT8_8-10","MT9_10-11","MT10_3-4","MT10_5-7","MT10_9-10","MT10_12-13","MT10_17-18","MT10_19-20","MT10_23","MT10_25-26","MT10_32-33","MT10_34-36","MT10_40-41","MT11_10","MT12_9-10"],"445":["MT7_26-27"],"616":["MT10_11"],"661":["MT9_12-13"],"1112":["MT8_11-12"],"2021":["MT13_20-21"],"2030":["MT9_27"],"te":["MT1_1","MT1_20","MT2_11","MT2_13","MT3_14","MT3_16","MT4_3","MT4_6","MT4_8-9","MT4_10","MT4_22","MT5_17","MT5_19","MT5_23-24","MT5_25-26","MT5_29-30","MT5_36","MT5_37","MT5_39","MT5_40","MT5_41","MT5_45","MT6_6","MT6_17-18","MT6_27","MT6_28-29","MT6_34","MT8_19-20","MT9_23","MT9_25-26","MT10_17-18","MT11_23-24","MT11_25","MT11_28","MT12_36-37","MT13_31-32"],"învăţa":["MT1_1","MT1_20","MT5_2","MT5_19","MT7_28-29","MT9_16-17","MT13_34-35","MT13_53-54"],"dumnezeu":["MT1_1","MT1_3","MT1_5-6","MT1_12-16","MT1_18","MT1_20","MT1_21","MT1_22","MT1_23","MT2_4","MT2_6","MT2_11","MT2_12","MT2_13","MT2_14-15","MT2_16","MT2_16-17","MT3_1","MT3_4","MT3_9","MT3_16-17","MT4_1","MT4_3","MT4_4","MT4_6","MT4_10","MT4_11","MT4_17","MT4_24","MT5_7","MT5_8","MT5_9","MT5_16","MT5_17","MT5_33-35","MT5_36","MT5_45","MT6_5","MT6_9","MT6_12","MT6_15","MT6_24","MT6_25","MT6_26","MT6_27","MT6_28-29","MT6_30","MT6_32-33","MT6_34","MT7_1","MT7_6","MT7_11","MT7_12","MT7_21","MT7_24-25","MT7_28-29","MT8_1","MT8_2","MT8_21-22","MT8_28","MT8_29","MT9_2","MT9_3-5","MT9_6-8","MT9_9","MT9_12-13","MT9_27","MT9_30-31","MT9_34","MT9_37-38","MT10_3-4","MT10_19-20","MT10_28","MT10_29-31","MT10_32-33","MT10_34-36","MT10_40-41","MT11_2-3","MT11_25","MT12_11-12","MT12_14-15","MT12_22-23","MT12_25-26","MT12_28","MT12_31-32","MT12_39-40","MT12_47-50","MT13_3","MT13_8","MT13_13","MT13_14-15","MT13_24-30","MT13_37-42","MT13_44","MT13_54-57"],"grăit":["MT1_1","MT1_22","MT5_21","MT5_22","MT11_4-6","MT11_10","MT13_3","MT13_51-52"],"supuşi":["MT1_1","MT2_1","MT8_8-10","MT13_57-58"],"iisus":["MT1_1","MT1_3-5","MT1_12-16","MT1_18","MT1_23","MT2_1","MT2_7","MT3_13-14","MT3_15","MT3_16","MT3_16-17","MT4_1","MT4_7","MT4_10","MT4_12-13","MT4_17","MT4_23","MT5_1","MT7_22-23","MT7_28-29","MT8_3-4","MT8_5","MT8_6-7","MT8_8-10","MT8_13","MT8_14-15","MT8_18","MT8_19-20","MT8_21-22","MT8_25-26","MT8_32-34","MT9_1","MT9_2","MT9_3-5","MT9_9","MT9_10-11","MT9_14","MT9_15","MT9_18-19","MT9_20-22","MT9_23","MT9_25-26","MT9_27","MT9_28","MT9_30-31","MT9_35","MT10_5-7","MT11_1","MT11_2-3","MT11_4-6","MT11_7","MT11_12","MT11_20","MT11_23-24","MT11_25","MT12_1","MT12_9-10","MT12_14-15","MT12_17","MT12_22-23","MT12_25-26","MT13_13","MT13_34-35","MT13_53-54","MT13_54-57","MT13_57-58"],"punea":["MT1_1"],"părinte":["MT1_2","MT3_9","MT11_25","MT11_26","MT11_27"],"seminţia":["MT1_2","MT2_1"],"binecuvânta":["MT1_2","MT2_11"],"neam":["MT1_2","MT1_5","MT1_12-16","MT2_3","MT5_13","MT5_14","MT12_39-40","MT12_43-45"],"înainte":["MT1_2","MT1_18","MT1_20","MT1_25","MT2_4","MT2_7","MT4_17","MT4_19-20","MT5_17","MT5_18","MT6_8","MT7_15-16","MT8_5","MT8_29","MT10_2","MT10_21","MT11_7","MT11_11","MT11_14","MT11_20","MT11_28","MT12_2-4","MT12_29","MT12_38","MT12_43-45","MT13_14-15","MT13_24-30","MT13_31-32","MT13_34-35","MT13_37-42","MT13_44","MT13_51-52"],"fiii":["MT1_2","MT5_9","MT5_45","MT6_14","MT7_9-10","MT7_22-23","MT8_11-12","MT9_15","MT10_2","MT11_21","MT13_37-42"],"slujnica":["MT1_2"],"seminţiip":["MT1_2"],"feciori":["MT1_3","MT2_21-22","MT10_37","MT13_54-57"],"prunci":["MT1_3","MT2_16","MT11_25"],"răutatea":["MT1_3","MT1_23","MT2_13","MT2_16","MT6_34","MT10_25-26","MT11_21","MT12_30"],"facă":["MT1_3","MT1_19","MT1_20","MT2_1","MT3_9","MT4_3","MT4_12-13","MT5_3","MT5_33-35","MT7_12","MT7_18","MT8_29","MT10_1","MT11_23-24","MT12_2-4","MT12_11-12","MT12_15-16"],"feciorul":["MT1_3"],"înlăuntrul":["MT1_3"],"abia":["MT1_3","MT1_7-11"],"scosese":["MT1_3"],"numit":["MT1_3","MT1_12-16","MT1_19","MT1_20","MT1_23","MT2_23","MT4_1","MT5_25-26","MT5_39","MT7_13","MT8_19-20","MT8_25-26","MT10_2","MT10_3-4","MT10_25-26","MT11_2-3","MT11_10","MT12_22-23","MT12_25-26","MT12_39-40","MT13_33"],"cea":["MT1_3","MT1_5","MT1_12-16","MT1_17","MT1_19","MT1_23","MT1_24","MT2_6","MT2_7","MT2_16","MT3_2","MT3_4","MT3_11","MT3_12","MT3_13-14","MT3_14","MT3_15-16","MT4_1","MT4_12-13","MT4_17","MT5_10","MT5_12","MT5_16","MT5_18","MT5_27","MT5_29-30","MT5_31-32","MT5_39","MT5_43-44","MT6_2","MT6_3","MT6_10","MT6_11","MT6_19-21","MT6_26","MT7_11","MT7_13","MT7_16-17","MT7_19-20","MT7_28-29","MT8_14-15","MT8_25-26","MT9_10-11","MT9_14","MT9_15","MT9_18-19","MT9_25-26","MT9_28","MT10_1","MT10_16","MT10_19-20","MT10_22","MT10_25-26","MT10_28","MT10_37","MT10_39","MT10_40-41","MT11_10","MT11_12","MT11_14","MT11_16-17","MT11_21-22","MT12_2-4","MT12_34-35","MT12_43-45","MT12_47-50","MT13_3","MT13_13","MT13_20-21","MT13_22","MT13_24-30","MT13_31-32","MT13_37-42","MT13_51-52"],"sfinţii":["MT1_3","MT3_4","MT5_43-44","MT13_24-30"],"vieţuit":["MT1_3"],"evanghelicească":["MT1_3","MT3_3"],"deşi":["MT1_3","MT1_17","MT9_10-11","MT9_18-19","MT9_20-22","MT9_23","MT11_7","MT11_29-30","MT12_2-4","MT12_42","MT13_10-12","MT13_33","MT13_51-52"],"unii":["MT1_3","MT1_17","MT2_7","MT3_12","MT5_5","MT5_9","MT5_18","MT5_22","MT5_47-48","MT6_5","MT7_15-16","MT9_3-5","MT9_20-22","MT10_8","MT10_22","MT11_2-3","MT11_4-6","MT11_25","MT12_25-26","MT12_31-32","MT12_38","MT13_13"],"aram":["MT1_3-5"],"41819span":["MT1_3-5"],"25span":["MT1_3-5","MT9_2"],"luk_2":["MT1_3-5"],"dataid=js6_23joshua":["MT1_3-5"],"iscoadele":["MT1_3-5"],"dataid=rt4_21421span":["MT1_5"],"332spanpprut":["MT1_5"],"așezământ":["MT1_5"],"1712span":["MT1_5-6"],"urie":["MT1_5-6"],"dataid=k111_431":["MT1_7-11"],"dataid=r13_161":["MT1_7-11"],"abiud":["MT1_12-16"],"socoti":["MT1_12-16","MT11_27"],"obşte":["MT1_12-16","MT6_25","MT12_25-26","MT13_8","MT13_10-12","MT13_53-54"],"despărţit":["MT1_17","MT3_7"],"nume":["MT1_17","MT1_23","MT3_7","MT10_40-41","MT10_42"],"egipt":["MT1_18","MT2_13","MT2_14-15","MT2_16","MT2_19-20","MT2_23"],"primejdii":["MT1_18","MT4_12-13","MT10_27"],"luare":["MT1_18"],"vădită":["MT1_19","MT7_15-16"],"tocmai":["MT1_19","MT1_20","MT12_38"],"poruncile":["MT1_19","MT3_3","MT5_17","MT5_19","MT5_21","MT10_38","MT11_29-30"],"dânsastrong":["MT1_19"],"iată":["MT1_20","MT1_23","MT2_1","MT2_9","MT2_11","MT2_13","MT2_19-20","MT3_10","MT3_16-17","MT4_11","MT5_15","MT5_28","MT7_2-5","MT8_2","MT8_23-24","MT8_29","MT8_32-34","MT9_2","MT9_10-11","MT9_18-19","MT9_20-22","MT9_32-33","MT10_16","MT11_2-3","MT11_8","MT11_10","MT11_18-19","MT12_2-4","MT12_9-10","MT12_17","MT12_28","MT12_39-40","MT12_41","MT12_42","MT12_46","MT12_47-50","MT13_3","MT13_51-52"],"domnului":["MT1_20","MT1_24","MT2_13","MT2_19-20","MT3_3","MT4_10","MT5_28","MT5_33-35","MT6_8","MT9_34","MT12_2-4","MT13_54-57"],"unele":["MT1_20","MT3_3","MT7_9-10","MT7_19-20","MT12_14-15","MT12_34","MT13_4-6","MT13_13"],"poate":["MT1_20","MT2_7","MT2_9","MT2_16","MT2_23","MT3_9","MT3_11","MT3_15-16","MT4_3","MT5_2","MT5_14","MT5_29-30","MT5_31-32","MT6_24","MT6_27","MT7_2-5","MT7_13","MT7_18","MT7_19-20","MT7_24-25","MT8_6-7","MT8_28","MT9_14","MT9_28","MT10_16","MT10_24-25","MT10_28","MT10_40-41","MT12_5-6","MT12_29","MT12_31-32","MT13_8","MT13_37-42","MT13_54-57"],"proorocul":["MT1_22","MT1_23","MT2_12","MT2_14-15","MT2_18","MT3_3","MT4_14-16","MT5_17","MT6_26","MT8_16-17","MT11_10","MT11_14","MT12_17","MT12_39-40","MT13_34-35"],"ştii":["MT1_22","MT3_3","MT12_34-35"],"răspundem":["MT1_23","MT13_13"],"da":["MT1_23","MT2_1","MT4_4","MT4_8-9","MT4_10","MT5_25-26","MT5_37","MT6_25","MT7_7-8","MT7_9-10","MT7_11","MT8_3-4","MT8_21-22","MT9_28","MT10_17-18","MT10_19-20","MT10_21","MT10_23","MT10_38","MT10_42","MT11_9","MT11_26","MT12_31-32","MT12_36-37","MT12_39-40","MT13_10-12","MT13_51-52"],"dataid=is7_14714span":["MT1_23"],"faptele":["MT1_23","MT5_16","MT5_20","MT5_22","MT6_1","MT7_26-27","MT10_12-13","MT11_2-3","MT11_19","MT13_8"],"trezvie":["MT1_24"],"înţelege":["MT1_25","MT2_11","MT3_11","MT5_5","MT5_45","MT6_17-18","MT10_40-41","MT11_14","MT11_28","MT12_7","MT12_22-23","MT12_43-45","MT13_3","MT13_14-15","MT13_18-19","MT13_23","MT13_34-35"],"1supdsup":["MT2_1"],"îngerească":["MT2_2","MT11_10","MT13_31-32"],"dinspre":["MT2_2","MT4_1"],"2supcsup":["MT2_2","MT4_2","MT9_2"],"învăţaţi":["MT2_4","MT4_19-20","MT9_12-13","MT10_9-10","MT10_27"],"pământul":["MT2_6","MT2_19-20","MT2_21-22","MT4_14-16","MT5_5","MT5_18","MT5_33-35","MT6_25","MT13_3","MT13_8"],"căpeteniile":["MT2_6","MT9_36"],"conducătorulspanp2":["MT2_6"],"class=biblerefapocalipsa_227spanppbine":["MT2_6"],"nazaret":["MT2_6","MT2_23","MT3_1"],"semănătura":["MT2_6"],"paşte":["MT2_6"],"turbure":["MT2_9","MT10_21","MT10_29-31"],"cuprind":["MT2_9"],"casei":["MT2_9","MT9_2","MT10_5-7","MT10_12-13","MT10_25-26","MT13_24-30","MT13_51-52"],"căutaup":["MT2_10"],"rămână":["MT2_11","MT9_12-13"],"strongcel":["MT2_11","MT3_11"],"fiestrong":["MT2_11","MT3_7"],"dumnezeirea":["MT2_11"],"urma":["MT2_12","MT8_19-20"],"pruncul":["MT2_13","MT2_14-15","MT2_19-20","MT2_21-22","MT2_23"],"duce":["MT2_13","MT4_1","MT4_12-13","MT6_13","MT7_13","MT7_14","MT8_8-10","MT12_43-45","MT13_44"],"pdeci":["MT2_14-15"],"cioplite":["MT2_14-15"],"ieşire":["MT2_16","MT6_32-33","MT6_34","MT8_11-12","MT12_11-12","MT13_44"],"omorâtori":["MT2_16"],"partea":["MT2_16"],"tăiaţi":["MT2_16","MT13_24-30","MT13_37-42"],"păcatelor":["MT2_16","MT3_1","MT3_5-6","MT3_11","MT3_16-17","MT5_12","MT9_3-5","MT11_10","MT11_28"],"acestap":["MT2_16-17","MT7_24-25"],"rama":["MT2_18"],"auzit":["MT2_18","MT4_3","MT5_21","MT5_27","MT5_33-35","MT5_38","MT5_43-44","MT11_15","MT13_4-6","MT13_9","MT13_43"],"grăindpspan":["MT2_18"],"picioarelor":["MT2_19","MT5_33-35"],"antipa":["MT2_21-22"],"strongîn":["MT2_21-22"],"dataid=lk2_39luke":["MT2_22","MT2_23"],"prooroci":["MT2_23","MT3_7","MT9_33","MT10_5-7","MT10_40-41","MT11_9","MT12_43-45","MT13_16-17"],"class=biblerefioan_16span":["MT3_1"],"locuia":["MT3_1","MT9_1"],"sileşte":["MT3_1-2","MT5_31-32","MT11_12"],"cerurilorspanpîmpărăţia":["MT3_2"],"dataid=lk1_76luke":["MT3_3","MT11_9"],"duhovniceşti":["MT3_3","MT6_32-33","MT7_9-10","MT11_11","MT12_31-32","MT13_9","MT13_10-12"],"4supasup":["MT3_4"],"dataid=mk1_6mark":["MT3_4"],"16spanppşi":["MT3_4"],"cămila":["MT3_4"],"îmbrăcăminte":["MT3_4","MT6_28-29"],"iordan":["MT3_5-6","MT3_13-14","MT3_16","MT4_14-16"],"duhuri":["MT3_7","MT12_43-45"],"dreptate":["MT3_7","MT5_6","MT5_10","MT5_23-24","MT6_32-33"],"socoteală":["MT3_7","MT6_6","MT8_28","MT11_14","MT12_36-37","MT13_51-52"],"vă":["MT3_9","MT3_11","MT3_12","MT4_1","MT4_19-20","MT5_11","MT5_12","MT5_14","MT5_16","MT5_22","MT5_28","MT5_31-32","MT5_33-35","MT5_39","MT5_43-44","MT5_46","MT6_5","MT6_7","MT6_8","MT6_9","MT6_15","MT6_19-21","MT6_25","MT6_28-29","MT6_34","MT7_6","MT7_9-10","MT7_12","MT7_22-23","MT8_25-26","MT9_3-5","MT10_14-15","MT10_16","MT10_17-18","MT10_19-20","MT10_23","MT10_25-26","MT10_27","MT10_28","MT10_29-31","MT10_32-33","MT10_40-41","MT11_19","MT11_28","MT12_5-6","MT12_27","MT12_28","MT12_31-32","MT12_36-37","MT12_41","MT12_43-45","MT13_14-15"],"bunăspanpnu":["MT3_10"],"gheeneip":["MT3_10"],"dupăstrong":["MT3_11"],"murirea":["MT3_11"],"îndestulare":["MT3_11"],"socotiţi":["MT3_12","MT5_5","MT5_14","MT5_17","MT9_3-5","MT10_34-36"],"arie":["MT3_12"],"spele":["MT3_13-14"],"nouă":["MT3_13-14","MT3_15","MT4_1","MT4_2","MT4_11","MT5_43-44","MT6_10","MT6_11","MT6_12","MT6_13","MT8_30-32","MT9_15","MT13_8","MT13_23","MT13_34-35","MT13_36","MT13_51-52"],"viistrong":["MT3_14"],"slavă":["MT3_15","MT6_7","MT8_3-4","MT8_18","MT9_20-22","MT9_29-30","MT12_17","MT12_19","MT12_47-50"],"15supcsup16supasup":["MT3_15-16"],"botezânduse":["MT3_15-16"],"iubirea":["MT3_15-16","MT6_24","MT6_32-33","MT11_25","MT11_26","MT12_11-12"],"duhppprecum":["MT3_16-17"],"vedea":["MT4_1","MT5_8","MT7_2-5","MT12_22-23","MT12_31-32","MT13_14-15"],"42spanppa":["MT4_2"],"lăcomiei":["MT4_3","MT4_11"],"44spanppdin":["MT4_4"],"slujeştispanp4":["MT4_10"],"2414span":["MT4_10"],"patimilor":["MT4_11","MT5_8"],"întemniţat":["MT4_12-13"],"1910span":["MT4_12-13"],"strongneftalistrong":["MT4_12-13"],"dataid=is9_191span":["MT4_14-16"],"luminăstrong":["MT4_14-16"],"slugile":["MT4_17","MT10_24-25","MT13_24-30"],"strongîmpărăţia":["MT4_17"],"ascultători":["MT4_19-20","MT10_1"],"dataid=dt33_9deuteronomy":["MT4_22"],"dumnezeuppiar":["MT4_22","MT6_25"],"învaţă":["MT4_23","MT5_2","MT5_12","MT5_14","MT5_20","MT6_14","MT7_9-10","MT7_21","MT9_16-17","MT9_29-30","MT10_8","MT10_9-10","MT10_24-25","MT10_28","MT10_42","MT11_1","MT12_17","MT12_19","MT13_51-52","MT13_53-54"],"îndelungata":["MT4_23"],"lunatici":["MT4_24"],"chinuia":["MT4_24"],"mulţimile":["MT5_1","MT7_28-29","MT9_6-8","MT9_33","MT9_36","MT11_7","MT12_22-23","MT13_36"],"săvârşim":["MT5_1","MT5_16"],"învăţătoreascăpspan":["MT5_1"],"dataid=ps1_1psalm":["MT5_2"],"duhulstrogp":["MT5_3"],"strongplângstrong":["MT5_4"],"3611span":["MT5_5"],"săturaspanp5":["MT5_6"],"lacrimippiar":["MT5_7"],"dataid=p12_191":["MT5_10"],"2135span":["MT5_12"],"lepădaţi":["MT5_13","MT11_19"],"călcată":["MT5_13"],"dataid=mk9_50950span":["MT5_13"],"dataid=pr4_18proverbs":["MT5_16"],"legi":["MT5_17","MT5_21"],"împlinesc":["MT5_17"],"vouăp":["MT5_18","MT7_28-29"],"povăţui":["MT5_19"],"prisosi":["MT5_20","MT13_10-12"],"aţi":["MT5_21","MT5_27","MT5_33-35","MT5_38","MT5_43-44","MT8_21-22","MT9_12-13","MT10_8","MT11_7","MT11_9","MT12_41","MT13_31-32"],"dataid=mk10_19mark":["MT5_21","MT5_27"],"1019span":["MT5_21","MT5_27"],"nehotărât":["MT5_21"],"poruncitep":["MT5_21"],"slujitori":["MT5_22"],"aspră":["MT5_22","MT13_4-6"],"dragoste":["MT5_22"],"focul":["MT5_22","MT5_39","MT10_42","MT13_22","MT13_37-42"],"uită":["MT5_28"],"dataid=pr6_25proverbs":["MT5_28"],"gheenăspanp5":["MT5_29-30"],"veninduşi":["MT5_29-30"],"înafară":["MT5_31-32"],"199span":["MT5_31-32"],"dataid=dt20_14deuteronomy":["MT5_31-32"],"dataid=ps47_3psalm":["MT5_33-35"],"jurământ":["MT5_37"],"dataid=ex21_24exodus":["MT5_38"],"frica":["MT5_38","MT8_25-26"],"dataid=c16_71":["MT5_39","MT5_40"],"lovire":["MT5_39"],"haine":["MT5_41","MT7_15-16","MT10_9-10","MT11_8"],"dataid=dt15_8158span":["MT5_42"],"împrumutul":["MT5_42"],"760spanppacum":["MT5_43-44"],"binecuvântaţi":["MT5_43-44"],"nedrepţispanp5":["MT5_45"],"dataid=lk6_35luke":["MT5_45"],"dataid=lv20_7207span":["MT5_47-48"],"dreptăţii2":["MT6_1"],"milostenia":["MT6_2","MT6_3","MT6_4","MT6_17-18"],"dreapta":["MT6_3","MT12_2-4"],"place":["MT6_5","MT11_16-17","MT11_19"],"bârfirea":["MT6_7"],"dese":["MT6_7"],"rugăciunep":["MT6_7"],"34span":["MT6_9","MT7_7-8","MT11_18-19"],"zippîncă":["MT6_11"],"1114spanppfiindcă":["MT6_12"],"ierte":["MT6_12"],"minep":["MT6_12","MT12_27"],"dataid=ep4_32ephesians":["MT6_14"],"simţirile":["MT6_17-18"],"dataid=jm5_2james":["MT6_19-21"],"dataid=lk12_21luke":["MT6_19-21"],"neagoniseală":["MT6_19-21","MT10_9-10","MT13_8"],"bogăţiei":["MT6_19-21"],"pironi":["MT6_22-23"],"slujească":["MT6_24"],"1613span":["MT6_24","MT10_19-20"],"1226span":["MT6_28-29"],"dataid=mt16_8matthew":["MT6_30"],"class=noteword63132supasup":["MT6_31-32"],"duceţi":["MT6_31-32"],"dataid=lk12_30luke":["MT6_32-33"],"înţelepciune":["MT6_32-33","MT7_26-27","MT8_11-12","MT8_28","MT10_11","MT10_17-18","MT10_19-20","MT11_14","MT11_20","MT12_36-37","MT13_10-12","MT13_43"],"grijindute":["MT6_34"],"osândind":["MT7_1"],"daţi":["MT7_6","MT7_9-10","MT7_11"],"întorcânduse":["MT7_6","MT9_20-22"],"neputinţăp":["MT7_6"],"289span":["MT7_7-8","MT12_5-6"],"dataid=mt21_22matthew":["MT7_7-8"],"dataid=lk11_13luke":["MT7_11"],"138spanpparată":["MT7_12"],"gonirile":["MT7_13"],"1128span30":["MT7_14"],"dataid=mc3_5micah":["MT7_15-16"],"dataid=lk6_44luke":["MT7_15-16","MT7_16-17","MT7_19-20"],"pomul":["MT7_16-17","MT7_19-20","MT12_33"],"altoi":["MT7_19-20"],"1316span":["MT7_22-23","MT10_24-25"],"1325span":["MT7_22-23"],"fugeau":["MT7_22-23"],"lucrează":["MT7_22-23","MT7_26-27","MT12_31-32","MT13_8"],"nechibzuit":["MT7_26-27"],"649span":["MT7_26-27"],"cade":["MT7_26-27","MT12_11-12"],"întinzând":["MT8_3-4","MT12_47-50"],"fugind":["MT8_3-4","MT8_18"],"împărăţiei":["MT8_11-12","MT9_35","MT13_10-12","MT13_18-19","MT13_37-42"],"apusuri":["MT8_11-12"],"ceasul":["MT8_13","MT9_20-22","MT10_19-20"],"sârguia":["MT8_19-20"],"dataid=lk8_24luke":["MT8_25-26","MT8_26-27"],"440spanppnu":["MT8_25-26"],"demonizaţispanp8":["MT8_28"],"dânşii":["MT8_28","MT10_5-7","MT10_9-10","MT12_14-15"],"aceeaspanp8":["MT8_28"],"mărturisinduşi":["MT8_29"],"trimitene":["MT8_30-32"],"dataid=lk8_33luke":["MT8_30-32","MT8_32-34"],"ţărm":["MT8_32-34"],"dataid=s26_92":["MT8_32-34"],"dataid=lk5_18luke":["MT9_1","MT9_2"],"dataid=mk2_5mark":["MT9_2"],"tămăduirea":["MT9_3-5"],"dataid=mt9_33matthew":["MT9_6-8"],"dataid=lk5_27luke":["MT9_9"],"primirea":["MT9_10-11"],"necurăţia":["MT9_12-13"],"sufărppîncă":["MT9_12-13"],"dataid=lk5_36luke":["MT9_16-17"],"403span4":["MT9_20-22"],"oprită":["MT9_20-22","MT13_7"],"buruiană":["MT9_20-22"],"sfărâmată":["MT9_20-22"],"856span":["MT9_30-31"],"limba":["MT9_32-33","MT12_22-23"],"1114spanppminunânduse":["MT9_33"],"necăjite":["MT9_36"],"scoată":["MT9_37-38","MT10_1"],"74span8":["MT10_1"],"plecaţi":["MT10_1"],"învăţăturăp":["MT10_1"],"dataid=jn13_21john":["MT10_3-4"],"întrarmează":["MT10_5-7"],"potrivit":["MT10_8"],"cugete":["MT10_8"],"voispanp10":["MT10_12-13","MT10_19-20"],"1012spanppvoieşte":["MT10_14-15"],"nădejde":["MT10_16","MT12_43-45","MT13_8"],"nevătămători":["MT10_16"],"dataid=lk21_12luke":["MT10_17-18"],"tăuppşii":["MT10_17-18"],"dataid=s223_22":["MT10_19-20"],"copiii":["MT10_21","MT13_54-57"],"urâţi":["MT10_22","MT10_23"],"ucigaşi":["MT10_23"],"destul":["MT10_24-25"],"ocările":["MT10_24-25"],"dataid=k21_22":["MT10_25-26"],"123spanppcele":["MT10_27"],"perii":["MT10_29-31"],"lepăda":["MT10_32-33","MT10_38"],"dataid=mk8_38mark":["MT10_32-33"],"838span":["MT10_32-33"],"dataid=jr9_4jeremiah":["MT10_34-36"],"1253span":["MT10_34-36"],"prietenilor":["MT10_34-36"],"dataid=lk9_23luke":["MT10_38"],"vechime":["MT10_38"],"grijeşte":["MT10_39"],"dataid=mk9_37mark":["MT10_40-41"],"937span":["MT10_40-41"],"1244span":["MT10_40-41"],"dataid=jn13_201320span":["MT10_40-41"],"dataid=k117_91":["MT10_40-41"],"primeştel":["MT10_40-41"],"sărăciei":["MT10_42"],"scripturi":["MT11_2-3","MT11_25","MT12_36-37"],"class=noteword22":["MT11_4-6","MT11_7","MT11_8"],"ceaţi":["MT11_7"],"dataid=lk7_25luke":["MT11_8"],"desfăteze":["MT11_8"],"moip":["MT11_8"],"hristosdumnezeu":["MT11_9"],"taspanp11":["MT11_10","MT11_26"],"botezătorulspanp11":["MT11_11"],"silinţă":["MT11_12"],"înţelegeţi":["MT11_14","MT13_14-15"],"audăspanp11":["MT11_15"],"tânguitspanp11":["MT11_16-17"],"neîmpăcarea":["MT11_16-17"],"aşap":["MT11_16-17"],"dataid=lk7_34luke":["MT11_18-19"],"nepocăiţi":["MT11_20"],"dataid=mt10_15matthew":["MT11_21","MT11_21-22","MT11_23-24"],"cenuşă":["MT11_21-22"],"pocăinţei":["MT11_21-22","MT12_43-45"],"săupspan":["MT11_27"],"flămânzit":["MT12_1","MT12_2-4"],"mâncat":["MT12_2-4","MT13_4-6"],"64spanppînvinuind":["MT12_2-4"],"foamea":["MT12_2-4"],"«călcau»":["MT12_5-6"],"66span7":["MT12_9-10"],"dataid=mk3_4mark":["MT12_13"],"nedarnice":["MT12_13"],"vileagspanp12":["MT12_15-16"],"422spanppnu":["MT12_19"],"1115spanppchiar":["MT12_24"],"diavolilor":["MT12_29"],"dataid=lk9_50luke":["MT12_30"],"ajute":["MT12_30"],"văd":["MT12_31-32","MT13_13","MT13_16-17"],"numindule":["MT12_31-32"],"dataid=mt7_17matthew":["MT12_33"],"«roada»":["MT12_33"],"«putredă»":["MT12_33"],"prisosul":["MT12_34-35"],"dataid=c11_221":["MT12_38"],"mirânduse":["MT12_38"],"1130spanppia":["MT12_39-40"],"dataid=lk11_31luke":["MT12_42"],"neputincioasă":["MT12_42"],"şapte":["MT12_43-45"],"sălăşluiesc":["MT12_43-45","MT13_31-32"],"rudenieppdeci":["MT12_47-50"],"class=noteword13":["MT13_1","MT13_3","MT13_4-6","MT13_7","MT13_8","MT13_9","MT13_10-12","MT13_13","MT13_14-15","MT13_16-17","MT13_18-19","MT13_20-21","MT13_22","MT13_23","MT13_24-30","MT13_31-32","MT13_33","MT13_34-35","MT13_36","MT13_37-42","MT13_43","MT13_44","MT13_45-46","MT13_47-50","MT13_51-52","MT13_53-54"],"adunat":["MT13_2","MT13_47-50"],"dataid=mk4_3mark":["MT13_3"],"43span":["MT13_3","MT13_22"],"3supbsup":["MT13_3"],"mergem":["MT13_3"],"semene":["MT13_3"],"85span6":["MT13_4-6"],"învârtoşat":["MT13_14-15"],"dataid=jn12_40john":["MT13_14-15"],"dataid=r29_72":["MT13_16-17"],"dataid=lk10_23luke":["MT13_16-17"],"calep":["MT13_18-19"],"dataid=gn26_12genesis":["MT13_23"],"2612span":["MT13_23"],"dataid=lk8_15luke":["MT13_23"],"815spanppde":["MT13_23"],"plivim":["MT13_24-30"],"dataid=mk4_28428span":["MT13_24-30"],"hristospp„sămânţa":["MT13_24-30"],"tăia":["MT13_24-30","MT13_37-42"],"dataid=lk13_20luke":["MT13_33"],"„aluat":["MT13_33"],"întregime":["MT13_33"],"întrebuinţat":["MT13_34-35"],"elineşti":["MT13_44"],"supuse":["MT13_44"],"închide":["MT13_45-46"],"prinşi":["MT13_47-50"],"„cărturari":["MT13_51-52"],"„din":["MT13_51-52"],"dataid=mk6_1mark":["MT13_53-54"],"necinstit":["MT13_57-58"],"câteva":["MT13_57-58"]}